virt_llm/__init__.py
virt_llm-0.1.0.dist-info/METADATA
virt_llm-0.1.0.dist-info/WHEEL
virt_llm-0.1.0.dist-info/top_level.txt
virt_llm-0.1.0.dist-info/RECORD
